pjdev_decorators/__about__.py
pjdev_decorators/__init__.py
pjdev_decorators/decorators.py
pjdev_decorators-4.6.3.dist-info/METADATA
pjdev_decorators-4.6.3.dist-info/WHEEL
pjdev_decorators-4.6.3.dist-info/licenses/LICENSE.txt
pjdev_decorators-4.6.3.dist-info/RECORD
